{
  "$schema": "https://turbo.build/schema.json",
  "globalDependencies": ["**/.env.*local"],
  "tasks": {
    "build": {
      "dependsOn": ["^build"],
      "outputs": ["apps/core/dist/**", "apps/core/.next/**", "!.next/cache/**"]
    },
    "dev": {
      "cache": false,
      "persistent": true
    },
    "start": {
      "dependsOn": ["build"],
      "cache": false,
      "persistent": true
    },
    "check": {
      "dependsOn": ["^check"],
      "outputs": []
    },
    "lint": {
      "dependsOn": ["^lint"],
      "outputs": []
    },
    "clean": {
      "cache": false
    },
    "db:push": {
      "cache": false
    },
    "type-check": {
      "dependsOn": ["^build"],
      "outputs": []
    },
    "db:generate": {
      "cache": false,
      "outputs": []
    },
    "db:migrate": {
      "cache": false,
      "outputs": []
    },
    "db:studio": {
      "cache": false,
      "persistent": true
    },
    "env:validate": {
      "cache": false
    },
    "env:generate": {
      "cache": false
    }
  }
}